diff_1c-6.6.9.dist-info/METADATA
diff_1c-6.6.9.dist-info/WHEEL
diff_1c-6.6.9.dist-info/entry_points.txt
diff_1c/__about__.py
diff_1c/__init__.py
diff_1c/__main__.py
diff_1c/cli.py
diff_1c/core.py
diff_1c/main.py
tests/__init__.py
tests/data/settings.yaml
tests/data/test.epf
tests/test_diff_1c.py
diff_1c-6.6.9.dist-info/RECORD
